MANIFEST.in
README.rst
VERSION
conftest.py
requirements.txt
setup.cfg
setup.py
PyRaut.egg-info/PKG-INFO
PyRaut.egg-info/SOURCES.txt
PyRaut.egg-info/dependency_links.txt
PyRaut.egg-info/top_level.txt
docs/Makefile
docs/conf.py
docs/index.rst
pyraut/__init__.py
pyraut/path.py
pyraut/processors.py
tests/test_complex.py
tests/test_default.py
tests/test_package.py
tests/test_path.py